streq/__init__.py
streq/circular.py
streq/distance.py
streq/seqtools.py
streq/sequences.yml
streq/utils.py
streq-0.0.2.dist-info/LICENSE
streq-0.0.2.dist-info/METADATA
streq-0.0.2.dist-info/WHEEL
streq-0.0.2.dist-info/top_level.txt
streq-0.0.2.dist-info/RECORD
